ruamel.ewmh-0.1.4-py2.7-nspkg.pth
ruamel.ewmh-0.1.4.dist-info/namespace_packages.txt
ruamel.ewmh-0.1.4.dist-info/WHEEL
ruamel.ewmh-0.1.4.dist-info/top_level.txt
ruamel.ewmh-0.1.4.dist-info/RECORD
ruamel.ewmh-0.1.4.dist-info/metadata.json
ruamel.ewmh-0.1.4.dist-info/METADATA
ruamel.ewmh-0.1.4.dist-info/DESCRIPTION.rst
ruamel.ewmh-0.1.4.dist-info/LICENSE.txt
ruamel/ewmh/__init__.py
ruamel/ewmh/ewmh.py
