Metadata-Version: 2.0
Name: ruamel.ewmh
Version: 0.1.4
Summary: retrieve and set window information on Linux (via Extended Window Manager Hints)
Home-page: https://bitbucket.org/ruamel/ewmh
Author: Anthon van der Neut
Author-email: a.van.der.neut@ruamel.eu
License: MIT license
Platform: UNKNOWN
Classifier: Development Status :: 4 - Beta
Classifier: Intended Audience :: Developers
Classifier: License :: OSI Approved :: MIT License
Classifier: Operating System :: OS Independent
Classifier: Programming Language :: Python
Requires-Dist: ruamel.base (>=1.0.0)
